img2hbirc/__init__.py
img2hbirc/cli.py
img2hbirc-1.0.1.dist-info/licenses/LICENSE
img2hbirc-1.0.1.dist-info/METADATA
img2hbirc-1.0.1.dist-info/WHEEL
img2hbirc-1.0.1.dist-info/entry_points.txt
img2hbirc-1.0.1.dist-info/top_level.txt
img2hbirc-1.0.1.dist-info/RECORD
