Metadata-Version: 2.4
Name: img2hbirc
Version: 1.0.1
Summary: Image to Half-block ANSI art with IRC color codes.
Author-email: Swee <meow@swee.codes>
License: Apache-2.0
Project-URL: Homepage, https://swee.codes/apps/img2text
Project-URL: Repository, https://git.swee.codes/swee/img2hbirc
Project-URL: Issues, https://git.swee.codes/swee/img2hbirc/issues
Project-URL: Changelog, https://git.swee.codes/swee/img2hbirc/releases
Classifier: Programming Language :: Python :: 3
Classifier: Operating System :: OS Independent
Requires-Python: >=3.9
License-File: LICENSE
Requires-Dist: typer
Requires-Dist: typing-extensions
Requires-Dist: pillow
Dynamic: license-file
